warno_mfw/__init__.py
warno_mfw/constants/__init__.py
warno_mfw/constants/enums.py
warno_mfw/constants/literals.py
warno_mfw/constants/misc.py
warno_mfw/constants/ndf.py
warno_mfw/constants/ndf_paths.py
warno_mfw/constants/paths.py
warno_mfw/context/__init__.py
warno_mfw/context/mod_creation.py
warno_mfw/context/unit_module.py
warno_mfw/creators/__init__.py
warno_mfw/creators/ammo.py
warno_mfw/creators/division.py
warno_mfw/creators/weapon.py
warno_mfw/creators/unit/__init__.py
warno_mfw/creators/unit/abc.py
warno_mfw/creators/unit/basic.py
warno_mfw/creators/unit/infantry.py
warno_mfw/creators/unit/towed.py
warno_mfw/creators/unit/utils/__init__.py
warno_mfw/creators/unit/utils/trait_def.py
warno_mfw/creators/unit/utils/trait_defs.py
warno_mfw/creators/unit/utils/infantry/__init__.py
warno_mfw/creators/unit/utils/infantry/_squad_keys.py
warno_mfw/creators/unit/utils/infantry/weapon.py
warno_mfw/creators/unit/utils/infantry/weapon_set.py
warno_mfw/creators/unit/utils/infantry/weapons.py
warno_mfw/managers/__init__.py
warno_mfw/managers/country.py
warno_mfw/managers/guid.py
warno_mfw/managers/localization.py
warno_mfw/managers/unit_id.py
warno_mfw/metadata/__init__.py
warno_mfw/metadata/division.py
warno_mfw/metadata/mod.py
warno_mfw/metadata/unit.py
warno_mfw/metadata/warno.py
warno_mfw/model/__init__.py
warno_mfw/model/deck_unite_rule.py
warno_mfw/model/infantry_squad_weapon_assignment_module_descriptor.py
warno_mfw/model/t_depiction_descriptor.py
warno_mfw/model/template_infantry_selector_tactic.py
warno_mfw/model/weapon_manager_module_descriptor.py
warno_mfw/unit_registration/__init__.py
warno_mfw/unit_registration/_types.py
warno_mfw/unit_registration/division_rule_lookup.py
warno_mfw/unit_registration/division_unit_registry.py
warno_mfw/unit_registration/new_src_unit_pair.py
warno_mfw/unit_registration/unit_group.py
warno_mfw/unit_registration/unit_registration_info.py
warno_mfw/unit_registration/unit_rules.py
warno_mfw/utils/__init__.py
warno_mfw/utils/bat.py
warno_mod_framework-0.0.0.dist-info/LICENSE
warno_mod_framework-0.0.0.dist-info/METADATA
warno_mod_framework-0.0.0.dist-info/WHEEL
warno_mod_framework-0.0.0.dist-info/top_level.txt
warno_mod_framework-0.0.0.dist-info/RECORD
